tests/__init__.py
tests/config.py
tests/test_auth.py
tests/test_core.py
tests/test_endpoints.py
tests/test_streaming.py
yacli/__init__.py
yacli/cli.py
yacli/common.py
yacli/constants.py
yacli/commands/__init__.py
yacli/commands/auth.py
yacli/commands/create.py
yacli/commands/pull.py
yacli/commands/sync.py
yacli/commands/update.py
yacli/helpers/__init__.py
yacli/helpers/save_data_from_request.py
yellowant/__init__.py
yellowant/advisory.py
yellowant/api.py
yellowant/compat.py
yellowant/endpoints.py
yellowant/exceptions.py
yellowant/helpers.py
yellowant/messageformat.py
yellowant/rtm_client.py
yellowant-0.0.34.dist-info/METADATA
yellowant-0.0.34.dist-info/RECORD
yellowant-0.0.34.dist-info/WHEEL
yellowant-0.0.34.dist-info/entry_points.txt
yellowant-0.0.34.dist-info/top_level.txt
yellowant-0.0.34.dist-info/zip-safe
