Metadata-Version: 2.1
Name: yellowant
Version: 0.0.34
Summary: Python wrapper for the YellowAnt API
Home-page: https://github.com/vishwa306/yellowant-python-sdk/tree/master
Author: Vishwa Krishnakumar
Author-email: vishwa@yellowant.com
License: The MIT License
Requires-Dist: pyaml
Requires-Dist: requests (>=2.1.0)
Requires-Dist: requests-oauthlib (>=0.4.0)
Requires-Dist: click
Requires-Dist: socketIO-client (==0.7.2)
